[
  {
    "ApiId": "/providers/microsoft.powerapps/apis/shared_sharepointonline",
    "CdpRevision": {
      "BaseUrl": "/",
      "LastChangedTimeString": "2023-10-30T18:14:11.1260000Z",
      "RevisionNumber": 1
    },
    "ConnectedDataSourceInfoNameMapping": {
      "{Attachments}": "Anexos",
      "{Attachments}@odata.type": "{Attachments} ({Attachments}@odata.type)",
      "{FilenameWithExtension}": "Nome de arquivo com extensão",
      "{FullPath}": "Caminho Completo",
      "{HasAttachments}": "Tem anexos",
      "{Identifier}": "Identificador",
      "{IsFolder}": "ÉPasta",
      "{Link}": "Link para o item",
      "{ModerationComment}": "Comentários associados à aprovação de conteúdo deste item de lista",
      "{ModerationStatus}": "Status de aprovação de conteúdo",
      "{Name}": "Nome",
      "{Path}": "Caminho da pasta",
      "{Thumbnail}": "Miniatura",
      "{TriggerWindowEndToken}": "Token de Fim da Janela de Acionamento",
      "{TriggerWindowStartToken}": "Token de Início da Janela de Acionamento",
      "{VersionNumber}": "Número da versão",
      "Author": "Criado por",
      "Author#Claims": "Criado por Claims",
      "ComplianceAssetId": "ID de Ativo de Conformidade",
      "Created": "Criado",
      "Editor": "Modificado por",
      "Editor#Claims": "Modificado por Claims",
      "field_0": "Data de análise",
      "field_10": "Enviar email",
      "field_11": "Email Enviado?",
      "field_12": "Status de prazo do envio do email",
      "field_13": "Email de confirmação?",
      "field_14": "Terá aditivo",
      "field_15": "Data de assinatura do aditivo 1",
      "field_16": "Finalização Estimada do aditivo 1",
      "field_17": "Enviar email2",
      "field_18": "Email Enviado?3",
      "field_19": "Status de prazo do envio do email4",
      "field_2": "Responsável contrato de gestão",
      "field_20": "Email de confirmação?5",
      "field_21": "Terá aditivo6",
      "field_22": "Data de assinatura do aditivo 2",
      "field_23": "Finalização do aditivo 2",
      "field_24": "Enviar email7",
      "field_25": "Email Enviado?8",
      "field_26": "Status de prazo do envio do email9",
      "field_27": "Email de confirmação?10",
      "field_28": "Terá aditivo11",
      "field_29": "Data de assinatura do aditivo 3",
      "field_3": "N° do contrato",
      "field_30": "Finalização do aditivo 3",
      "field_31": "Enviar email12",
      "field_32": "Email Enviado?13",
      "field_33": "Status de prazo do envio do email14",
      "field_34": "Email de confirmação?15",
      "field_35": "Terá aditivo16",
      "field_36": "Data de assinatura do aditivo 4",
      "field_37": "Finalização do aditivo 4",
      "field_38": "Enviar email17",
      "field_39": "Email Enviado?18",
      "field_4": "Objeto da contratação",
      "field_40": "Status de prazo do envio do email19",
      "field_41": "Email de confirmação?20",
      "field_42": "Terá aditivo21",
      "field_43": "Data de assinatura do aditivo 5",
      "field_44": "Finalização do aditivo 5",
      "field_5": "Empresa Contratada",
      "field_6": "Fiscal Técnico responsável",
      "field_7": "Lista de dados de email",
      "field_8": "Início do contrato",
      "field_9": "Finalização do contrato",
      "ID": "ID",
      "Modified": "Modificado",
      "OData__ColorTag": "Pressione Delete para excluir o ícone.",
      "OData__ModernAudienceTargetUserField": "Audiência",
      "OData__ModernAudienceTargetUserField#Claims": "Audiência Claims",
      "OData__ModernAudienceTargetUserField@odata.type": "OData__ModernAudienceTargetUserField (OData__ModernAudienceTargetUserField@odata.type)",
      "Title": "Contrato de Gestão"
    },
    "DatasetName": "https://agepeixevivo.sharepoint.com/sites/RH",
    "EncodeDataset": true,
    "IsSampleData": false,
    "IsWritable": true,
    "Name": "Acompanhamento dos Termos aditivos da Agência",
    "Type": "ConnectedDataSourceInfo"
  }
]